<?xml version="1.0" encoding="UTF-8"?>
<con:soapui-project id="644a8223-8af3-44a6-9ec8-900cd0c7b4d7" activeEnvironment="Default environment" name="XPSimple" resourceRoot="" soapui-version="6.0.0" xmlns:con="http://eviware.com/soapui/config"><con:settings/><con:interface xsi:type="con:WsdlInterface" id="011b692e-86f7-44cb-9d8e-8ea978cfa116" wsaVersion="NONE" name="HelloWorldWebServiceSoap12" type="wsdl" bindingName="{http://shadow.org/}HelloWorldWebServiceSoap12" soapVersion="1_2" anonymous="optional" definition="http://eremeev-w8/servers/wsdl/simple/server.asmx?wsdl" xmlns:xsi="http://www.w3.org/2001/XMLSchema-instance"><con:settings/><con:definitionCache/><con:endpoints><con:endpoint>http://eremeev-w8/servers/wsdl/simple/server.asmx</con:endpoint></con:endpoints><con:operation id="84e34bf2-09bd-400c-b958-75ad15e92f0e" isOneWay="false" action="http://shadow.org/AdditionFigures" name="AdditionFigures" bindingOperationName="AdditionFigures" type="Request-Response" inputName="" receivesAttachments="false" sendsAttachments="false" anonymous="optional"><con:settings/><con:call id="902bbc71-6a47-40c9-b49f-14af10ba4f38" name="Request 1"><con:settings/><con:encoding>UTF-8</con:encoding><con:endpoint>http://eremeev-w8/servers/wsdl/simple/server.asmx</con:endpoint><con:request><![CDATA[<soap:Envelope xmlns:soap="http://www.w3.org/2003/05/soap-envelope" xmlns:shad="http://shadow.org/">\r
   <soap:Header/>\r
   <soap:Body>\r
      <shad:AdditionFigures>\r
         <shad:first>?</shad:first>\r
         <shad:second>?</shad:second>\r
      </shad:AdditionFigures>\r
   </soap:Body>\r
</soap:Envelope>]]></con:request><con:wsaConfig mustUnderstand="NONE" version="200508" action="http://shadow.org/HelloWorldWebServiceSoap/AdditionFiguresRequest"/></con:call></con:operation><con:operation id="69dc43aa-165f-4401-996c-242a4ca57cf2" isOneWay="false" action="http://shadow.org/GetSmallRandomIntegerFigure" name="GetSmallRandomIntegerFigure" bindingOperationName="GetSmallRandomIntegerFigure" type="Request-Response" inputName="" receivesAttachments="false" sendsAttachments="false" anonymous="optional"><con:settings/><con:call id="e60d8a9e-0a1f-412e-83e3-516c64dd9868" name="Request 1"><con:settings/><con:encoding>UTF-8</con:encoding><con:endpoint>http://eremeev-w8/servers/wsdl/simple/server.asmx</con:endpoint><con:request><![CDATA[<soap:Envelope xmlns:soap="http://www.w3.org/2003/05/soap-envelope" xmlns:shad="http://shadow.org/">\r
   <soap:Header/>\r
   <soap:Body>\r
      <shad:GetSmallRandomIntegerFigure/>\r
   </soap:Body>\r
</soap:Envelope>]]></con:request><con:wsaConfig mustUnderstand="NONE" version="200508" action="http://shadow.org/HelloWorldWebServiceSoap/GetSmallRandomIntegerFigureRequest"/></con:call></con:operation><con:operation id="4d90e59e-ffad-4c72-b15b-46e23542a0dd" isOneWay="false" action="http://shadow.org/GetStringLength" name="GetStringLength" bindingOperationName="GetStringLength" type="Request-Response" inputName="" receivesAttachments="false" sendsAttachments="false" anonymous="optional"><con:settings/><con:call id="370376d3-a14e-495b-aad6-9cb3837270c9" name="Request 1"><con:settings/><con:encoding>UTF-8</con:encoding><con:endpoint>http://eremeev-w8/servers/wsdl/simple/server.asmx</con:endpoint><con:request><![CDATA[<soap:Envelope xmlns:soap="http://www.w3.org/2003/05/soap-envelope" xmlns:shad="http://shadow.org/">\r
   <soap:Header/>\r
   <soap:Body>\r
      <shad:GetStringLength>\r
         <!--Optional:-->\r
         <shad:value>?</shad:value>\r
      </shad:GetStringLength>\r
   </soap:Body>\r
</soap:Envelope>]]></con:request><con:wsaConfig mustUnderstand="NONE" version="200508" action="http://shadow.org/HelloWorldWebServiceSoap/GetStringLengthRequest"/></con:call></con:operation><con:operation id="75eadaaf-8d1d-4529-a04f-b9cff423d9dd" isOneWay="false" action="http://shadow.org/HelloWorld" name="HelloWorld" bindingOperationName="HelloWorld" type="Request-Response" inputName="" receivesAttachments="false" sendsAttachments="false" anonymous="optional"><con:settings/><con:call id="e94b6d4e-255d-4df1-b002-7930a85c35f0" name="Request 1"><con:settings/><con:encoding>UTF-8</con:encoding><con:endpoint>http://eremeev-w8/servers/wsdl/simple/server.asmx</con:endpoint><con:request><![CDATA[<soap:Envelope xmlns:soap="http://www.w3.org/2003/05/soap-envelope" xmlns:shad="http://shadow.org/">\r
   <soap:Header/>\r
   <soap:Body>\r
      <shad:HelloWorld>\r
         <!--Optional:-->\r
         <shad:name>?</shad:name>\r
      </shad:HelloWorld>\r
   </soap:Body>\r
</soap:Envelope>]]></con:request><con:wsaConfig mustUnderstand="NONE" version="200508" action="http://shadow.org/HelloWorldWebServiceSoap/HelloWorldRequest"/></con:call></con:operation><con:operation id="b1b48d31-8157-4637-a52a-68604a653db1" isOneWay="false" action="http://shadow.org/ReturnInputString" name="ReturnInputString" bindingOperationName="ReturnInputString" type="Request-Response" inputName="" receivesAttachments="false" sendsAttachments="false" anonymous="optional"><con:settings/><con:call id="b014561d-87c6-420e-89bb-b0caf0401024" name="Request 1"><con:settings/><con:encoding>UTF-8</con:encoding><con:endpoint>http://eremeev-w8/servers/wsdl/simple/server.asmx</con:endpoint><con:request><![CDATA[<soap:Envelope xmlns:soap="http://www.w3.org/2003/05/soap-envelope" xmlns:shad="http://shadow.org/">\r
   <soap:Header/>\r
   <soap:Body>\r
      <shad:ReturnInputString>\r
         <!--Optional:-->\r
         <shad:value>?</shad:value>\r
      </shad:ReturnInputString>\r
   </soap:Body>\r
</soap:Envelope>]]></con:request><con:wsaConfig mustUnderstand="NONE" version="200508" action="http://shadow.org/HelloWorldWebServiceSoap/ReturnInputStringRequest"/></con:call></con:operation></con:interface><con:interface xsi:type="con:WsdlInterface" id="6d5e0125-d034-465d-bbfd-684929a2e5f3" wsaVersion="NONE" name="HelloWorldWebServiceSoap" type="wsdl" bindingName="{http://shadow.org/}HelloWorldWebServiceSoap" soapVersion="1_1" anonymous="optional" definition="http://eremeev-w8/servers/wsdl/simple/server.asmx?wsdl" xmlns:xsi="http://www.w3.org/2001/XMLSchema-instance"><con:settings/><con:definitionCache type="TEXT" rootPart="http://eremeev-w8/servers/wsdl/simple/server.asmx?wsdl"><con:part><con:url>http://eremeev-w8/servers/wsdl/simple/server.asmx?wsdl</con:url><con:content><![CDATA[<wsdl:definitions targetNamespace="http://shadow.org/" xmlns:s="http://www.w3.org/2001/XMLSchema" xmlns:soap12="http://schemas.xmlsoap.org/wsdl/soap12/" xmlns:http="http://schemas.xmlsoap.org/wsdl/http/" xmlns:mime="http://schemas.xmlsoap.org/wsdl/mime/" xmlns:tns="http://shadow.org/" xmlns:soap="http://schemas.xmlsoap.org/wsdl/soap/" xmlns:tm="http://microsoft.com/wsdl/mime/textMatching/" xmlns:soapenc="http://schemas.xmlsoap.org/soap/encoding/" xmlns:wsdl="http://schemas.xmlsoap.org/wsdl/">
  <wsdl:types>
    <s:schema elementFormDefault="qualified" targetNamespace="http://shadow.org/">
      <s:element name="HelloWorld">
        <s:complexType>
          <s:sequence>
            <s:element minOccurs="0" maxOccurs="1" name="name" type="s:string"/>
          </s:sequence>
        </s:complexType>
      </s:element>
      <s:element name="HelloWorldResponse">
        <s:complexType>
          <s:sequence>
            <s:element minOccurs="0" maxOccurs="1" name="HelloWorldResult" type="s:string"/>
          </s:sequence>
        </s:complexType>
      </s:element>
      <s:element name="AdditionFigures">
        <s:complexType>
          <s:sequence>
            <s:element minOccurs="1" maxOccurs="1" name="first" type="s:double"/>
            <s:element minOccurs="1" maxOccurs="1" name="second" type="s:double"/>
          </s:sequence>
        </s:complexType>
      </s:element>
      <s:element name="AdditionFiguresResponse">
        <s:complexType>
          <s:sequence>
            <s:element minOccurs="1" maxOccurs="1" name="AdditionFiguresResult" type="s:double"/>
          </s:sequence>
        </s:complexType>
      </s:element>
      <s:element name="GetSmallRandomIntegerFigure">
        <s:complexType/>
      </s:element>
      <s:element name="GetSmallRandomIntegerFigureResponse">
        <s:complexType>
          <s:sequence>
            <s:element minOccurs="1" maxOccurs="1" name="GetSmallRandomIntegerFigureResult" type="s:int"/>
          </s:sequence>
        </s:complexType>
      </s:element>
      <s:element name="GetStringLength">
        <s:complexType>
          <s:sequence>
            <s:element minOccurs="0" maxOccurs="1" name="value" type="s:string"/>
          </s:sequence>
        </s:complexType>
      </s:element>
      <s:element name="GetStringLengthResponse">
        <s:complexType>
          <s:sequence>
            <s:element minOccurs="1" maxOccurs="1" name="GetStringLengthResult" type="s:int"/>
          </s:sequence>
        </s:complexType>
      </s:element>
      <s:element name="ReturnInputString">
        <s:complexType>
          <s:sequence>
            <s:element minOccurs="0" maxOccurs="1" name="value" type="s:string"/>
          </s:sequence>
        </s:complexType>
      </s:element>
      <s:element name="ReturnInputStringResponse">
        <s:complexType>
          <s:sequence>
            <s:element minOccurs="0" maxOccurs="1" name="ReturnInputStringResult" type="s:string"/>
          </s:sequence>
        </s:complexType>
      </s:element>
    </s:schema>
  </wsdl:types>
  <wsdl:message name="HelloWorldSoapIn">
    <wsdl:part name="parameters" element="tns:HelloWorld"/>
  </wsdl:message>
  <wsdl:message name="HelloWorldSoapOut">
    <wsdl:part name="parameters" element="tns:HelloWorldResponse"/>
  </wsdl:message>
  <wsdl:message name="AdditionFiguresSoapIn">
    <wsdl:part name="parameters" element="tns:AdditionFigures"/>
  </wsdl:message>
  <wsdl:message name="AdditionFiguresSoapOut">
    <wsdl:part name="parameters" element="tns:AdditionFiguresResponse"/>
  </wsdl:message>
  <wsdl:message name="GetSmallRandomIntegerFigureSoapIn">
    <wsdl:part name="parameters" element="tns:GetSmallRandomIntegerFigure"/>
  </wsdl:message>
  <wsdl:message name="GetSmallRandomIntegerFigureSoapOut">
    <wsdl:part name="parameters" element="tns:GetSmallRandomIntegerFigureResponse"/>
  </wsdl:message>
  <wsdl:message name="GetStringLengthSoapIn">
    <wsdl:part name="parameters" element="tns:GetStringLength"/>
  </wsdl:message>
  <wsdl:message name="GetStringLengthSoapOut">
    <wsdl:part name="parameters" element="tns:GetStringLengthResponse"/>
  </wsdl:message>
  <wsdl:message name="ReturnInputStringSoapIn">
    <wsdl:part name="parameters" element="tns:ReturnInputString"/>
  </wsdl:message>
  <wsdl:message name="ReturnInputStringSoapOut">
    <wsdl:part name="parameters" element="tns:ReturnInputStringResponse"/>
  </wsdl:message>
  <wsdl:portType name="HelloWorldWebServiceSoap">
    <wsdl:operation name="HelloWorld">
      <wsdl:input message="tns:HelloWorldSoapIn"/>
      <wsdl:output message="tns:HelloWorldSoapOut"/>
    </wsdl:operation>
    <wsdl:operation name="AdditionFigures">
      <wsdl:input message="tns:AdditionFiguresSoapIn"/>
      <wsdl:output message="tns:AdditionFiguresSoapOut"/>
    </wsdl:operation>
    <wsdl:operation name="GetSmallRandomIntegerFigure">
      <wsdl:input message="tns:GetSmallRandomIntegerFigureSoapIn"/>
      <wsdl:output message="tns:GetSmallRandomIntegerFigureSoapOut"/>
    </wsdl:operation>
    <wsdl:operation name="GetStringLength">
      <wsdl:input message="tns:GetStringLengthSoapIn"/>
      <wsdl:output message="tns:GetStringLengthSoapOut"/>
    </wsdl:operation>
    <wsdl:operation name="ReturnInputString">
      <wsdl:input message="tns:ReturnInputStringSoapIn"/>
      <wsdl:output message="tns:ReturnInputStringSoapOut"/>
    </wsdl:operation>
  </wsdl:portType>
  <wsdl:binding name="HelloWorldWebServiceSoap" type="tns:HelloWorldWebServiceSoap">
    <soap:binding transport="http://schemas.xmlsoap.org/soap/http"/>
    <wsdl:operation name="HelloWorld">
      <soap:operation soapAction="http://shadow.org/HelloWorld" style="document"/>
      <wsdl:input>
        <soap:body use="literal"/>
      </wsdl:input>
      <wsdl:output>
        <soap:body use="literal"/>
      </wsdl:output>
    </wsdl:operation>
    <wsdl:operation name="AdditionFigures">
      <soap:operation soapAction="http://shadow.org/AdditionFigures" style="document"/>
      <wsdl:input>
        <soap:body use="literal"/>
      </wsdl:input>
      <wsdl:output>
        <soap:body use="literal"/>
      </wsdl:output>
    </wsdl:operation>
    <wsdl:operation name="GetSmallRandomIntegerFigure">
      <soap:operation soapAction="http://shadow.org/GetSmallRandomIntegerFigure" style="document"/>
      <wsdl:input>
        <soap:body use="literal"/>
      </wsdl:input>
      <wsdl:output>
        <soap:body use="literal"/>
      </wsdl:output>
    </wsdl:operation>
    <wsdl:operation name="GetStringLength">
      <soap:operation soapAction="http://shadow.org/GetStringLength" style="document"/>
      <wsdl:input>
        <soap:body use="literal"/>
      </wsdl:input>
      <wsdl:output>
        <soap:body use="literal"/>
      </wsdl:output>
    </wsdl:operation>
    <wsdl:operation name="ReturnInputString">
      <soap:operation soapAction="http://shadow.org/ReturnInputString" style="document"/>
      <wsdl:input>
        <soap:body use="literal"/>
      </wsdl:input>
      <wsdl:output>
        <soap:body use="literal"/>
      </wsdl:output>
    </wsdl:operation>
  </wsdl:binding>
  <wsdl:binding name="HelloWorldWebServiceSoap12" type="tns:HelloWorldWebServiceSoap">
    <soap12:binding transport="http://schemas.xmlsoap.org/soap/http"/>
    <wsdl:operation name="HelloWorld">
      <soap12:operation soapAction="http://shadow.org/HelloWorld" style="document"/>
      <wsdl:input>
        <soap12:body use="literal"/>
      </wsdl:input>
      <wsdl:output>
        <soap12:body use="literal"/>
      </wsdl:output>
    </wsdl:operation>
    <wsdl:operation name="AdditionFigures">
      <soap12:operation soapAction="http://shadow.org/AdditionFigures" style="document"/>
      <wsdl:input>
        <soap12:body use="literal"/>
      </wsdl:input>
      <wsdl:output>
        <soap12:body use="literal"/>
      </wsdl:output>
    </wsdl:operation>
    <wsdl:operation name="GetSmallRandomIntegerFigure">
      <soap12:operation soapAction="http://shadow.org/GetSmallRandomIntegerFigure" style="document"/>
      <wsdl:input>
        <soap12:body use="literal"/>
      </wsdl:input>
      <wsdl:output>
        <soap12:body use="literal"/>
      </wsdl:output>
    </wsdl:operation>
    <wsdl:operation name="GetStringLength">
      <soap12:operation soapAction="http://shadow.org/GetStringLength" style="document"/>
      <wsdl:input>
        <soap12:body use="literal"/>
      </wsdl:input>
      <wsdl:output>
        <soap12:body use="literal"/>
      </wsdl:output>
    </wsdl:operation>
    <wsdl:operation name="ReturnInputString">
      <soap12:operation soapAction="http://shadow.org/ReturnInputString" style="document"/>
      <wsdl:input>
        <soap12:body use="literal"/>
      </wsdl:input>
      <wsdl:output>
        <soap12:body use="literal"/>
      </wsdl:output>
    </wsdl:operation>
  </wsdl:binding>
  <wsdl:service name="HelloWorldWebService">
    <wsdl:port name="HelloWorldWebServiceSoap" binding="tns:HelloWorldWebServiceSoap">
      <soap:address location="http://eremeev-w8/servers/wsdl/simple/server.asmx"/>
    </wsdl:port>
    <wsdl:port name="HelloWorldWebServiceSoap12" binding="tns:HelloWorldWebServiceSoap12">
      <soap12:address location="http://eremeev-w8/servers/wsdl/simple/server.asmx"/>
    </wsdl:port>
  </wsdl:service>
</wsdl:definitions>]]></con:content><con:type>http://schemas.xmlsoap.org/wsdl/</con:type></con:part></con:definitionCache><con:endpoints><con:endpoint>http://eremeev-w8/servers/wsdl/simple/server.asmx</con:endpoint></con:endpoints><con:operation id="e4f2c7eb-6ffe-4a64-a2d3-c1a611974253" isOneWay="false" action="http://shadow.org/AdditionFigures" name="AdditionFigures" bindingOperationName="AdditionFigures" type="Request-Response" inputName="" receivesAttachments="false" sendsAttachments="false" anonymous="optional"><con:settings/><con:call id="c8012827-9784-41b2-b1c2-0d22468b6613" name="Request 1"><con:settings/><con:encoding>UTF-8</con:encoding><con:endpoint>http://eremeev-w8/servers/wsdl/simple/server.asmx</con:endpoint><con:request><![CDATA[<soapenv:Envelope xmlns:soapenv="http://schemas.xmlsoap.org/soap/envelope/" xmlns:shad="http://shadow.org/">\r
   <soapenv:Header/>\r
   <soapenv:Body>\r
      <shad:AdditionFigures>\r
         <shad:first>?</shad:first>\r
         <shad:second>?</shad:second>\r
      </shad:AdditionFigures>\r
   </soapenv:Body>\r
</soapenv:Envelope>]]></con:request><con:wsaConfig mustUnderstand="NONE" version="200508" action="http://shadow.org/AdditionFigures"/></con:call></con:operation><con:operation id="32aca19a-3486-41e5-b102-536b9abbb1bf" isOneWay="false" action="http://shadow.org/GetSmallRandomIntegerFigure" name="GetSmallRandomIntegerFigure" bindingOperationName="GetSmallRandomIntegerFigure" type="Request-Response" inputName="" receivesAttachments="false" sendsAttachments="false" anonymous="optional"><con:settings/><con:call id="bbeda223-8ccc-4872-85c9-8357d4d19a52" name="Request 1"><con:settings/><con:encoding>UTF-8</con:encoding><con:endpoint>http://eremeev-w8/servers/wsdl/simple/server.asmx</con:endpoint><con:request><![CDATA[<soapenv:Envelope xmlns:soapenv="http://schemas.xmlsoap.org/soap/envelope/" xmlns:shad="http://shadow.org/">\r
   <soapenv:Header/>\r
   <soapenv:Body>\r
      <shad:GetSmallRandomIntegerFigure/>\r
   </soapenv:Body>\r
</soapenv:Envelope>]]></con:request><con:wsaConfig mustUnderstand="NONE" version="200508" action="http://shadow.org/GetSmallRandomIntegerFigure"/></con:call></con:operation><con:operation id="4d26ef98-0ad3-4f9d-bbd0-9bf5fc208d38" isOneWay="false" action="http://shadow.org/GetStringLength" name="GetStringLength" bindingOperationName="GetStringLength" type="Request-Response" inputName="" receivesAttachments="false" sendsAttachments="false" anonymous="optional"><con:settings/><con:call id="3262253b-c02a-49c4-b2d3-7fadf9be9c5d" name="Request 1"><con:settings/><con:encoding>UTF-8</con:encoding><con:endpoint>http://eremeev-w8/servers/wsdl/simple/server.asmx</con:endpoint><con:request><![CDATA[<soapenv:Envelope xmlns:soapenv="http://schemas.xmlsoap.org/soap/envelope/" xmlns:shad="http://shadow.org/">\r
   <soapenv:Header/>\r
   <soapenv:Body>\r
      <shad:GetStringLength>\r
         <!--Optional:-->\r
         <shad:value>?</shad:value>\r
      </shad:GetStringLength>\r
   </soapenv:Body>\r
</soapenv:Envelope>]]></con:request><con:wsaConfig mustUnderstand="NONE" version="200508" action="http://shadow.org/GetStringLength"/></con:call></con:operation><con:operation id="d5ec84b7-ef7a-4b67-b411-e7de3c3e6a51" isOneWay="false" action="http://shadow.org/HelloWorld" name="HelloWorld" bindingOperationName="HelloWorld" type="Request-Response" inputName="" receivesAttachments="false" sendsAttachments="false" anonymous="optional"><con:settings/><con:call id="52f0bfd2-7328-466f-b361-406f83ffca3f" name="Request 1"><con:settings/><con:encoding>UTF-8</con:encoding><con:endpoint>http://eremeev-w8/servers/wsdl/simple/server.asmx</con:endpoint><con:request><![CDATA[<soapenv:Envelope xmlns:soapenv="http://schemas.xmlsoap.org/soap/envelope/" xmlns:shad="http://shadow.org/">\r
   <soapenv:Header/>\r
   <soapenv:Body>\r
      <shad:HelloWorld>\r
         <!--Optional:-->\r
         <shad:name>?</shad:name>\r
      </shad:HelloWorld>\r
   </soapenv:Body>\r
</soapenv:Envelope>]]></con:request><con:wsaConfig mustUnderstand="NONE" version="200508" action="http://shadow.org/HelloWorld"/></con:call></con:operation><con:operation id="39034bed-1e1d-402e-aa14-81c31bb52916" isOneWay="false" action="http://shadow.org/ReturnInputString" name="ReturnInputString" bindingOperationName="ReturnInputString" type="Request-Response" inputName="" receivesAttachments="false" sendsAttachments="false" anonymous="optional"><con:settings/><con:call id="af361a41-781a-4fc2-8c22-c9ce5760d94f" name="Request 1"><con:settings/><con:encoding>UTF-8</con:encoding><con:endpoint>http://eremeev-w8/servers/wsdl/simple/server.asmx</con:endpoint><con:request><![CDATA[<soapenv:Envelope xmlns:soapenv="http://schemas.xmlsoap.org/soap/envelope/" xmlns:shad="http://shadow.org/">\r
   <soapenv:Header/>\r
   <soapenv:Body>\r
      <shad:ReturnInputString>\r
         <!--Optional:-->\r
         <shad:value>?</shad:value>\r
      </shad:ReturnInputString>\r
   </soapenv:Body>\r
</soapenv:Envelope>]]></con:request><con:wsaConfig mustUnderstand="NONE" version="200508" action="http://shadow.org/ReturnInputString"/></con:call></con:operation></con:interface><con:properties/><con:wssContainer/><con:databaseConnectionContainer/><con:oAuth2ProfileContainer/></con:soapui-project>